databricks-clay/placeholder.py
dataclay/placeholder.py
databricks_clay-0.0.1.dist-info/METADATA
databricks_clay-0.0.1.dist-info/WHEEL
databricks_clay-0.0.1.dist-info/top_level.txt
databricks_clay-0.0.1.dist-info/RECORD
