Metadata-Version: 2.1
Name: databricks-clay
Version: 0.0.1
Summary: Databricks Deployment Utils
Home-page: https://databricks-clay.readthedocs.io/en/latest/
Author: Shaun Ryan
Author-email: shaun_chiburi@hotmail.com
License: MIT
Platform: UNKNOWN
Classifier: License :: OSI Approved :: MIT License
Classifier: Programming Language :: Python :: 3
Classifier: Programming Language :: Python :: 3.7
Requires-Dist: PyYAML
